ring_attention_pytorch/__init__.py
ring_attention_pytorch/distributed.py
ring_attention_pytorch/ring.py
ring_attention_pytorch/ring_attention.py
ring_attention_pytorch/ring_flash_attention.py
ring_attention_pytorch/ring_flash_attention_cuda.py
ring_attention_pytorch/tensor_typing.py
ring_attention_pytorch/tree_attn_decoding.py
ring_attention_pytorch/triton_flash_attn.py
ring_attention_pytorch/zig_zag_attention.py
ring_attention_pytorch-0.5.20.dist-info/licenses/LICENSE
ring_attention_pytorch-0.5.20.dist-info/METADATA
ring_attention_pytorch-0.5.20.dist-info/WHEEL
ring_attention_pytorch-0.5.20.dist-info/top_level.txt
ring_attention_pytorch-0.5.20.dist-info/RECORD
